Workbook

Sheet assumptions
A1: assumption_id | B1: variable | C1: value | D1: unit | E1: year | F1: geography | G1: source_id | H1: confidence | I1: notes
A2: DEF1 | B2: Total Addressable Market（TAM，总可及市场，理论上所有目标需求对应的收入池） | C2: 术语定义 | G2: 术语 | H2: 高 | I2: 本模型只输出情景，不把 TAM 当已验证事实
A3: DEF2 | B3: Serviceable Available Market（SAM，可服务市场，产品和地域实际覆盖的收入池） | C3: 术语定义 | G3: 术语 | H3: 高 | I3: SAM 必须小于或等于相同口径 TAM
A4: DEF3 | B4: Serviceable Obtainable Market（SOM，可获得市场，给定期间可现实取得的收入池） | C4: 术语定义 | G4: 术语 | H4: 高 | I4: SOM 必须小于或等于相同口径 SAM
A5: DEF4 | B5: Chinese Yuan Renminbi（CNY，人民币元，本工作簿金额的币种单位） | C5: 术语定义 | G5: 术语 | H5: 高 | I5: 所有人民币模型行使用 CNY
A6: DEF5 | B6: 模型标签 | C6: [外部事实]/[用户假设]/[模型估算] | G6: 分类 | H6: 高 | I6: 三类信息不得互相升级
A7: F1 | B7: 2023工业企业营业收入 | C7: 152400000000000 | D7: 人民币元 | E7: 2023 | F7: 中国大陆 | G7: [S1] | H7: 高 | I7: [外部事实] 国家统计局口径；不是软件支出
A8: F2 | B8: 制造业企业法人单位 | C8: 4048000 | D8: 个法人单位 | E8: 2023 | F8: 中国大陆 | G8: [S1] | H8: 高 | I8: [外部事实] 不是工厂、产线或客户数
A9: U1 | B9: 可服务客户占制造法人比例 | C9: 0.01 | D9: 比例 | E9: 2026 | F9: 中国大陆 | G9: [用户假设] | H9: 低 | I9: 不得写成外部渗透率
A10: U2 | B10: 质检软件年支出 | C10: 120000 | D10: 人民币元/客户/年 | E10: 2026 | F10: 中国大陆 | G10: [用户假设] | H10: 低 | I10: 不得用含硬件/定制/调试的整机价格 [S4] 替代
A11: U3 | B11: 三年可获得渗透率 | C11: 0.08 | D11: 比例 | E11: 2026-2028 | F11: 中国大陆 | G11: [用户假设] | H11: 低 | I11: 数字化率 [S2] 不是视觉渗透率
A12: U4 | B12: 工业收入中质检软件支出率 | C12: 0.0002 | D12: 比例 | E12: 2026 | F12: 中国大陆 | G12: [用户假设] | H12: 低 | I12: 仅用于顶部敏感性情景
A13: U5 | B13: 顶部市场可服务比例 | C13: 0.6 | D13: 比例 | E13: 2026 | F13: 中国大陆 | G13: [用户假设] | H13: 低 | I13: 仅用于顶部敏感性情景
A14: M1 | B14: 自上而下 SOM 情景 | C14: =top_down!G4 | D14: 人民币元/年 | E14: 2026 | F14: 中国大陆 | G14: [S1]+[用户假设] | H14: 低 | I14: [模型估算] 不是市场事实
A15: M2 | B15: 自下而上 SOM 情景 | C15: =bottom_up!G4 | D15: 人民币元/年 | E15: 2026 | F15: 中国大陆 | G15: [S1]+[用户假设] | H15: 低 | I15: [模型估算] 优先作尽调基准，仍需验证
A16: B1 | B16: 三组行业绝对额不可合并 | C16: 181.47/395.4/>400 | D16: 人民币亿元 | E16: 2024-2025 | F16: 中国大陆 | G16: [S3][S6][S7] | H16: 低 | I16: 定义分别为剔除集成市场转引、市场转引、总产值；不平均
A17: B2 | B17: 智能工厂与典型产线只作边界 | C17: 30000+/70道 | D17: 工厂/视觉系统 | E17: 2024-2025 | F17: 中国大陆 | G17: [S8][S10] | H17: 中 | I17: 领先样本和典型高端手机线，不外推全国

Sheet top_down
A1: line_id | B1: level | C1: parent_line_id | D1: market_item | E1: base_value | F1: filter_or_share | G1: calculated_value | H1: formula | I1: currency | J1: year | K1: source_id | L1: notes
A2: T1 | B2: TAM | D2: 工业收入支出率情景 | E2: 152400000000000 | F2: 0.0002 | G2: =E2*F2 | H2: =E2*F2 | I2: CNY | J2: 2026 | K2: [S1]+[U4] | L2: [模型估算] 304.8 亿元；支出率为用户假设，不是已验证 TAM
A3: T2 | B3: SAM | C3: T1 | D3: 可服务范围情景 | E3: =G2 | F3: 0.6 | G3: =E3*F3 | H3: =E3*F3 | I3: CNY | J3: 2026 | K3: [S1]+[U4]+[U5] | L3: [模型估算] 182.88 亿元
A4: T3 | B4: SOM | C4: T2 | D4: 三年可获得情景 | E4: =G3 | F4: 0.08 | G4: =E4*F4 | H4: =E4*F4 | I4: CNY | J4: 2026-2028 | K4: [S1]+[U3]+[U4]+[U5] | L4: [模型估算] 14.6304 亿元

Sheet bottom_up
A1: line_id | B1: segment | C1: customer_count | D1: units_per_customer | E1: annual_price_or_spend | F1: penetration_rate | G1: calculated_value | H1: formula | I1: currency | J1: year | K1: source_id | L1: notes
A2: B1 | B2: 全部制造法人上界 | C2: 4048000 | D2: 1 | E2: 120000 | F2: 1 | G2: =C2*D2*E2*F2 | H2: =C2*D2*E2*F2 | I2: CNY | J2: 2026 | K2: [S1]+[U2] | L2: TAM 情景上界；法人不是客户，不能当事实
A3: B2 | B3: 用户假设的可服务客户 | C3: =C2*1% | D3: 1 | E3: 120000 | F3: 1 | G3: =C3*D3*E3*F3 | H3: =C3*D3*E3*F3 | I3: CNY | J3: 2026 | K3: [S1]+[U1]+[U2] | L3: SAM 情景；1% 为用户假设
A4: B3 | B4: 三年可获得客户 | C4: =C3 | D4: 1 | E4: 120000 | F4: 0.08 | G4: =C4*D4*E4*F4 | H4: =C4*D4*E4*F4 | I4: CNY | J4: 2026-2028 | K4: [S1]+[U1]+[U2]+[U3] | L4: SOM 情景 3.88608 亿元；不是市场事实

Sheet reconciliation
A1: metric | B1: top_down_value | C1: bottom_up_value | D1: difference | E1: difference_pct | F1: explanation | G1: preferred_value | H1: reason
A2: TAM | B2: =top_down!G2 | C2: =bottom_up!G2 | D2: =ABS(B2-C2) | E2: =D2/MAX(B2,C2) | F2: 顶部用工业收入支出率，底部用全部制造法人和软件年支出；两者均被用户假设放大，不能据差值取平均 | G2: 不选点估计 | H2: 先验证纯软件收入与客户定义
A3: SAM | B3: =top_down!G3 | C3: =bottom_up!G3 | D3: =ABS(B3-C3) | E3: =D3/MAX(B3,C3) | F3: 顶部服务比例与底部可服务客户比例口径不同 | G3: =C3 | H3: 底部变量更可访谈验证，但仍是低置信情景
A4: SOM | B4: =top_down!G4 | C4: =bottom_up!G4 | D4: =ABS(B4-C4) | E4: =D4/MAX(B4,C4) | F4: 顶部与底部相差约 73%；不平均，保留分歧 | G4: =C4 | H4: 采用更窄的 3.88608 亿元作尽调基准，不宣称市场事实

Sheet orthogonality_check
A1: item_a | B1: item_b | C1: overlap_risk | D1: overlap_description | E1: resolution | F1: status
A2: 安防视频监控 | B2: 工业产线质检软件 | C2: 是 | D2: 视觉技术可重叠但买方预算和应用不同 | E2: 排除安防预算 | F2: clear
A3: 硬件/光源/相机 | B3: 软件许可/订阅/维护 | C3: 是 | D3: 整机合同常含硬件、软件、定制、调试 [S4] | E3: 本模型只保留用户给定软件年支出，不用整机平均销售价格 | F3: clear
A4: 整线自动化集成 | B4: 工业视觉软件 | C4: 是 | D4: 181.47 亿元口径声称剔除集成，但只是年报二次转引 [S3] | E4: 不把 181.47 亿元作为本模型输入 | F4: clear
A5: 法人单位 | B5: 工厂/产线/客户 | C5: 是 | D5: 404.8 万是法人，不是装机点 [S1] | E5: 以 U1 折减并保留敏感性 | F5: needs_review
A6: 数字化/工业互联网/人工智能使用 | B6: 机器视觉渗透率 | C6: 是 | D6: 统计口径不是机器视觉 [S2] | E6: 不使用该比例；渗透率只保留 U3 用户假设 | F6: clear
A7: 智能工厂样本/高端手机典型线 | B7: 全国制造业 | C7: 是 | D7: 领先样本 [S8] 与典型场景 [S10] 不能外推 | E7: 只作访谈分层，不进入点估计 | F7: clear

Sheet sources
A1: source_id | B1: source_name | C1: source_type | D1: url_or_location | E1: date | F1: fields_supported | G1: reliability
A2: [S1] | B2: 国家统计局第五次全国经济普查工业结果 | C2: 政府 | D2: https://www.stats.gov.cn/xxgk/jd/sjjd2020/202502/t20250227_1958812.html | E2: 2025-02-27 | F2: 工业收入、制造法人单位 | G2: 高
A3: [S2] | B3: 国家统计局企业数字化转型 | C3: 政府 | D3: https://www.stats.gov.cn/xxgk/jd/sjjd2020/202502/t20250227_1958814.html | E3: 2025-02-28 | F3: 数字化率反向边界 | G3: 高
A4: [S3] | B4: 奥普特 2025 年年度报告 | C4: 公司年报 | D4: https://www.optmv.com/Upload/File/202604/b1017ba56d8544ec91339d3714aed6e2.pdf | E4: 2026-04-03 | F4: 公司收入、181.47 亿元二次转引 | G4: 中高
A5: [S4] | B5: 双元科技第二轮问询回复 | C5: 监管披露 | D5: https://static.sse.com.cn/stock/disclosure/announcement/c/202303/001185_20230331_MG77.pdf | E5: 2023-03-31 | F5: 整机系统价、验收滞后 | G5: 高
A6: [S5] | B6: 中国机器视觉产业联盟报告发布页 | C6: 行业协会 | D6: https://www.china-vision.org/user/bilin.html | E6: 2025-06-19 | F6: 2024 销售额增速；绝对额/样本缺失 | G6: 中
A7: [S6] | B7: 凌云光 2025 VisionChina 活动稿 | C7: 公司材料 | D7: https://www.lusterinc.com/%E6%99%BA%E9%80%A0%E6%96%B0%E8%A7%86%E7%95%8C%EF%BC%81%E5%87%8C%E4%BA%91%E5%85%89%E4%BA%AE%E7%9B%B82025-visionchina%E5%8C%97%E4%BA%AC%E5%B1%95/ | E7: 2025-06-19 | F7: 395.4 亿元二次转引 | G7: 低
A8: [S7] | B8: 凌云光 2026 VisionChina 活动稿 | C8: 公司材料 | D8: https://www.lusterinc.com/%E4%BB%8E%E5%A4%A7%E5%92%96%E8%A7%82%E7%82%B9%E5%88%B0%E7%A1%AC%E6%A0%B8%E5%B1%95%E5%93%81%EF%BC%8C%E5%87%8C%E4%BA%91%E5%85%89-x-jai%E7%9A%84visionchina%E4%B9%8B%E6%97%85/ | E8: 2026-06-26 | F8: >400 亿元总产值 | G8: 低
A9: [S8] | B9: 工业和信息化部智能工厂进展 | C9: 政府 | D9: https://wap.miit.gov.cn/xwfb/gxdt/sjdt/art/2025/art_70c95052e16e44eb9bb49eae85f71e70.html | E9: 2025-02-07 | F9: 智能工厂分级样本 | G9: 高
A10: [S10] | B10: 智能检测装备产业发展研究报告——机器视觉篇 | C10: 技术白皮书 | D10: https://www.cesi.cn/images/editor/20240621/20240621150737979.pdf | E10: 2024-07-18 | F10: 高端手机典型线、数据孤岛 | G10: 中高
A11: STATE | B11: 研究状态：ready | C11: 状态 | D11: 本工作簿 | E11: 2026-07-29 | F11: 外部事实/用户假设/模型估算分离；结论为情景而非市场事实 | G11: 高
