Workbook

Sheet investment_terms
A1: investment_amount | B1: pre_money_valuation | C1: post_money_valuation | D1: initial_ownership | E1: security_type | F1: option_pool | G1: currency | H1: source_id | I1: notes | J1: investment_year
A2: 10 | B2: 90 | C2: 100 | D2: =A2/C2 -> 0.1 | E2: 普通股 | F2: 0 | G2: CNY 万元 | H2: S1 | I2: 同股同权；无分红；各笔现金流均按年末发生 | J2: 2026

Sheet financial_forecast
A1: year | B1: revenue | C1: gross_margin | D1: gross_profit | E1: EBITDA | F1: net_income | G1: cash_burn | H1: ending_cash | I1: source_id | J1: notes | K1: opening_cash
A2: 2027 | B2: 30 | C2: 0.5 | D2: =B2*C2 -> 15 | E2: 10 | F2: 5 | G2: 10 | H2: =K2-G2 -> 90 | I2: S1 | J2: 现金为简化经营情景，不含未来融资；期初现金独立给定 | K2: 100
A3: 2028 | B3: 50 | C3: 0.5 | D3: =B3*C3 -> 25 | E3: 10 | F3: 5 | G3: 10 | H3: =K3-G3 -> 80 | I3: S1 | J3: 现金为简化经营情景，不含未来融资；期初现金独立给定 | K3: =H2 -> 90
A4: 2029 | B4: 70 | C4: 0.5 | D4: =B4*C4 -> 35 | E4: 10 | F4: 5 | G4: 10 | H4: =K4-G4 -> 70 | I4: S1 | J4: 现金为简化经营情景，不含未来融资；期初现金独立给定 | K4: =H3 -> 80
A5: 2030 | B5: 90 | C5: 0.5 | D5: =B5*C5 -> 45 | E5: 10 | F5: 5 | G5: 10 | H5: =K5-G5 -> 60 | I5: S1 | J5: 现金为简化经营情景，不含未来融资；期初现金独立给定 | K5: =H4 -> 70
A6: 2031 | B6: 100 | C6: 0.5 | D6: =B6*C6 -> 50 | E6: 10 | F6: 5 | G6: 10 | H6: =K6-G6 -> 50 | I6: S1 | J6: 现金为简化经营情景，不含未来融资；期初现金独立给定 | K6: =H5 -> 60

Sheet financing_dilution
A1: round | B1: year | C1: new_money | D1: pre_money_valuation | E1: post_money_valuation | F1: investor_participates | G1: pro_rata_amount | H1: dilution_pct | I1: ownership_after_round | J1: source_id | K1: notes
A2: A | B2: 2027 | C2: 100 | D2: 400 | E2: =C2+D2 -> 500 | F2: 否 | G2: 0 | H2: =C2/E2 -> 0.2 | I2: =(investment_terms!D2*D2+G2)/E2 -> 0.08 | J2: S1

Sheet exit_scenarios
A1: scenario | B1: exit_year | C1: exit_metric | D1: exit_metric_value | E1: exit_multiple | F1: enterprise_value | G1: net_debt_or_cash | H1: equity_value | I1: source_id | J1: notes
A2: 保守 | B2: 2031 | C2: 收入 | D2: 50 | E2: 5 | F2: =D2*E2 -> 250 | G2: 10 | H2: =F2-G2 -> 240 | I2: S1 | J2: 净债务正数；全部为假设
A3: 中性 | B3: 2031 | C3: 收入 | D3: 100 | E3: 5 | F3: =D3*E3 -> 500 | G3: 10 | H3: =F3-G3 -> 490 | I3: S1 | J3: 净债务正数；全部为假设
A4: 乐观 | B4: 2031 | C4: 收入 | D4: 150 | E4: 5 | F4: =D4*E4 -> 750 | G4: 10 | H4: =F4-G4 -> 740 | I4: S1 | J4: 净债务正数；全部为假设

Sheet ownership
A1: year_or_round | B1: ownership_start | C1: dilution_pct | D1: pro_rata_investment | E1: ownership_end | F1: notes
A2: 2027 | B2: =investment_terms!D2 -> 0.1 | C2: =financing_dilution!H2 -> 0.2 | D2: =financing_dilution!G2 -> 0 | E2: =financing_dilution!I2 -> 0.08 | F2: 普通股逐轮稀释

Sheet returns
A1: scenario | B1: invested_capital | C1: exit_year | D1: final_ownership | E1: exit_equity_value | F1: proceeds | G1: MOIC | H1: IRR | I1: key_driver
A2: 保守 | B2: =investment_terms!A2+SUM(financing_dilution!G2) -> 10 | C2: 2031 | D2: =ownership!E2 -> 0.08 | E2: =exit_scenarios!H2 -> 240 | F2: =D2*E2 -> 19.2 | G2: =F2/B2 -> 1.92 | H2: =G2^(1/(C2-investment_terms!J2))-1 -> 0.1393581 | I2: 退出收入与估值倍数；此示例没有跟投
A3: 中性 | B3: =investment_terms!A2+SUM(financing_dilution!G2) -> 10 | C3: 2031 | D3: =ownership!E2 -> 0.08 | E3: =exit_scenarios!H3 -> 490 | F3: =D3*E3 -> 39.2 | G3: =F3/B3 -> 3.92 | H3: =G3^(1/(C3-investment_terms!J2))-1 -> 0.31418714 | I3: 退出收入与估值倍数；此示例没有跟投
A4: 乐观 | B4: =investment_terms!A2+SUM(financing_dilution!G2) -> 10 | C4: 2031 | D4: =ownership!E2 -> 0.08 | E4: =exit_scenarios!H4 -> 740 | F4: =D4*E4 -> 59.2 | G4: =F4/B4 -> 5.92 | H4: =G4^(1/(C4-investment_terms!J2))-1 -> 0.42713265 | I4: 退出收入与估值倍数；此示例没有跟投

Sheet sensitivity
A1: variable | B1: low_case | C1: base_case | D1: high_case | E1: impact_on_MOIC | F1: impact_on_IRR
A2: 中性退出倍数 | B2: 4 | C2: 5 | D2: 6 | E2: =returns!G3 -> 3.92 | F2: =returns!H3 -> 0.31418714

Sheet sources
A1: source_id | B1: source_name | C1: source_type | D1: url_or_location | E1: date | F1: fields_supported | G1: reliability
A2: S1 | B2: 虚构回归情景 | C2: 用户假设 | D2: examples/README.md | E2: 2026-10-18 | F2: 全部假设；单位：万元，市场模型除外 | G2: 假设计算，不代表事实
